poms/__init__.py
poms-0.0.0.dist-info/METADATA
poms-0.0.0.dist-info/WHEEL
poms-0.0.0.dist-info/top_level.txt
poms-0.0.0.dist-info/RECORD
