Metadata-Version: 2.1
Name: poms
Version: 0.0.0
Summary: T.B.A.
Home-page: https://github.com/not-so-fat/poms
Author: @not-so-fat
Author-email: conjurer.not.so.fat@gmail.com
License: UNKNOWN
Platform: UNKNOWN
Classifier: Programming Language :: Python :: 3
Classifier: License :: OSI Approved :: MIT License
Classifier: Operating System :: OS Independent
Requires-Python: >=3.6
Requires-Dist: pandas (==1.2.4)
Requires-Dist: numpy (==1.20.0)
Requires-Dist: scipy (==1.6.2)
Requires-Dist: scikit-learn (==0.24.1)
Requires-Dist: mlflow (==1.20.1)
